seapy/__init__.py
seapy/cdl_parser.py
seapy/constituents.npz
seapy/debug.py
seapy/environ.py
seapy/filt.py
seapy/hawaii.py
seapy/lib.py
seapy/mapping.py
seapy/oa.py
seapy/plot.py
seapy/progressbar.py
seapy/qserver.py
seapy/tidal_energy.py
seapy/tide.py
seapy/timeout.py
seapy/external/hindices.cp37-win_amd64.pyd
seapy/external/oalib.cp37-win_amd64.pyd
seapy/hawaii_coast/hawaii.dbf
seapy/hawaii_coast/hawaii.shp
seapy/hawaii_coast/hawaii.shx
seapy/model/__init__.py
seapy/model/grid.py
seapy/model/hycom.py
seapy/model/lib.py
seapy/model/soda.py
seapy/roms/__init__.py
seapy/roms/analysis.py
seapy/roms/boundary.py
seapy/roms/clim.py
seapy/roms/ezgrid.py
seapy/roms/forcing.py
seapy/roms/initial.py
seapy/roms/interp.py
seapy/roms/lib.py
seapy/roms/ncgen.py
seapy/roms/obs.py
seapy/roms/obsgen.py
seapy/roms/psource.py
seapy/roms/tide.py
seapy/roms/cdl/adsen.cdl
seapy/roms/cdl/bry_unlimit.cdl
seapy/roms/cdl/clm_ts.cdl
seapy/roms/cdl/frc_bulk.cdl
seapy/roms/cdl/frc_direct.cdl
seapy/roms/cdl/frc_fluxclm.cdl
seapy/roms/cdl/frc_qcorr.cdl
seapy/roms/cdl/frc_rivers.cdl
seapy/roms/cdl/frc_srelax.cdl
seapy/roms/cdl/frc_tides.cdl
seapy/roms/cdl/frc_wave.cdl
seapy/roms/cdl/frc_windstress.cdl
seapy/roms/cdl/ini_hydro.cdl
seapy/roms/cdl/nudge_coef.cdl
seapy/roms/cdl/roms_grid.cdl
seapy/roms/cdl/s4dvar_obs.cdl
seapy/roms/cdl/s4dvar_obs_rays.cdl
seapy/roms/cdl/s4dvar_std_b.cdl
seapy/roms/cdl/s4dvar_std_f.cdl
seapy/roms/cdl/s4dvar_std_i.cdl
seapy/roms/cdl/s4dvar_std_m.cdl
seapy/roms/cdl/zlevel_1d.cdl
seapy/roms/cdl/zlevel_1d_grid.cdl
seapy/roms/cdl/zlevel_2d.cdl
seapy/roms/cdl/zlevel_2d_grid.cdl
seapy/roms/cdl/zlevel_microbe_1d.cdl
seapy/roms/cdl/zlevel_microbe_2d.cdl
seapy/roms/cobalt/__init__.py
seapy/roms/cobalt/bry.cdl
seapy/roms/cobalt/clim.cdl
seapy/roms/cobalt/cobalt.py
seapy/roms/cobalt/frc_bulk.cdl
seapy/roms/cobalt/frc_cobalt.cdl
seapy/roms/cobalt/his.cdl
seapy/roms/cobalt/ini.cdl
seapy/roms/cobalt/nudge.cdl
seapy/roms/cobalt/zevel_dia.cdl
seapy/roms/cobalt/zlevel.cdl
seapy_ocean-0.5.2.dist-info/LICENSE.txt
seapy_ocean-0.5.2.dist-info/METADATA
seapy_ocean-0.5.2.dist-info/WHEEL
seapy_ocean-0.5.2.dist-info/top_level.txt
seapy_ocean-0.5.2.dist-info/RECORD
