Metadata-Version: 2.1
Name: seapy-ocean
Version: 0.5.2
Summary: State Estimation and Analysis in PYthon
Home-page: https://github.com/powellb/seapy
Author: Brian Powell
Author-email: powellb@hawaii.edu
License: MIT
Platform: UNKNOWN
Classifier: Programming Language :: Python :: 3.6
Classifier: License :: OSI Approved :: MIT License
Requires-Dist: basemap
Requires-Dist: h5py
Requires-Dist: joblib
Requires-Dist: netcdf4
Requires-Dist: numpy
Requires-Dist: numpy-groupies
Requires-Dist: scipy
